odoo/addons/mail_activity_form/README.rst
odoo/addons/mail_activity_form/__init__.py
odoo/addons/mail_activity_form/__manifest__.py
odoo/addons/mail_activity_form/demo/mail_activity_type.xml
odoo/addons/mail_activity_form/i18n/mail_activity_form.pot
odoo/addons/mail_activity_form/models/__init__.py
odoo/addons/mail_activity_form/models/mail_activity.py
odoo/addons/mail_activity_form/models/mail_activity_type.py
odoo/addons/mail_activity_form/readme/CONTRIBUTORS.rst
odoo/addons/mail_activity_form/readme/DESCRIPTION.rst
odoo/addons/mail_activity_form/readme/ROADMAP.rst
odoo/addons/mail_activity_form/readme/USAGE.rst
odoo/addons/mail_activity_form/static/description/icon.png
odoo/addons/mail_activity_form/static/description/index.html
odoo/addons/mail_activity_form/tests/__init__.py
odoo/addons/mail_activity_form/tests/test_mail_activity_form.py
odoo13_addon_mail_activity_form-13.0.1.0.1.dev6.dist-info/METADATA
odoo13_addon_mail_activity_form-13.0.1.0.1.dev6.dist-info/WHEEL
odoo13_addon_mail_activity_form-13.0.1.0.1.dev6.dist-info/top_level.txt
odoo13_addon_mail_activity_form-13.0.1.0.1.dev6.dist-info/RECORD
